mayat/AST.py
mayat/Checker.py
mayat/Result.py
mayat/__init__.py
mayat/args.py
mayat/driver.py
mayat/install_langs.py
mayat/main.py
mayat/frontends/C.py
mayat/frontends/Python.py
mayat/frontends/TS_C.py
mayat/frontends/TS_Java.py
mayat/frontends/TS_Python.py
mayat/frontends/__init__.py
mayat/result_viewer/__init__.py
mayat/result_viewer/app.py
mayat-1.1.1.dist-info/LICENSE.txt
mayat-1.1.1.dist-info/METADATA
mayat-1.1.1.dist-info/WHEEL
mayat-1.1.1.dist-info/top_level.txt
mayat-1.1.1.dist-info/RECORD
