Metadata-Version: 2.1
Name: mayat
Version: 1.1.1
Summary: AST-based code similarity detection tool
Author-email: "Tian(Maxwell) Yang" <ty1146@nyu.edu>
License: MIT License
Project-URL: Repository, https://github.com/AnubisLMS/Mayat
Classifier: Programming Language :: Python :: 3
Classifier: Operating System :: OS Independent
Classifier: Intended Audience :: Education
Classifier: Topic :: Education
Requires-Python: >=3.10
License-File: LICENSE.txt
Requires-Dist: clang
Requires-Dist: tree-sitter
Requires-Dist: tqdm
Requires-Dist: GitPython
Requires-Dist: flask
